chaitu_210_hw_greeting-1.0.dist-info/DESCRIPTION.rst
chaitu_210_hw_greeting-1.0.dist-info/METADATA
chaitu_210_hw_greeting-1.0.dist-info/RECORD
chaitu_210_hw_greeting-1.0.dist-info/WHEEL
chaitu_210_hw_greeting-1.0.dist-info/metadata.json
chaitu_210_hw_greeting-1.0.dist-info/top_level.txt
hellow/__init__.py
hellow/greeting.py
